cjm_plugin_system/__init__.py
cjm_plugin_system/_modidx.py
cjm_plugin_system/cli.py
cjm_plugin_system/core/__init__.py
cjm_plugin_system/core/interface.py
cjm_plugin_system/core/manager.py
cjm_plugin_system/core/metadata.py
cjm_plugin_system/core/proxy.py
cjm_plugin_system/core/scheduling.py
cjm_plugin_system/core/worker.py
cjm_plugin_system/utils/__init__.py
cjm_plugin_system/utils/validation.py
cjm_plugin_system-0.0.16.dist-info/licenses/LICENSE
tests_manual/__init__.py
tests_manual/dummy_plugin.py
tests_manual/test_federation.py
tests_manual/test_full_system.py
tests_manual/test_phase1.py
tests_manual/test_scheduling.py
tests_manual/test_whisper_integration.py
tests_manual/test_zombie_pact.py
cjm_plugin_system-0.0.16.dist-info/METADATA
cjm_plugin_system-0.0.16.dist-info/WHEEL
cjm_plugin_system-0.0.16.dist-info/entry_points.txt
cjm_plugin_system-0.0.16.dist-info/top_level.txt
cjm_plugin_system-0.0.16.dist-info/RECORD
