Metadata-Version: 2.4
Name: cjm-plugin-system
Version: 0.0.16
Summary: Generic plugin system with discovery, configuration validation, and runtime management for extensible Python applications.
Home-page: https://github.com/cj-mills/cjm-plugin-system
Author: Christian J. Mills
Author-email: 9126128+cj-mills@users.noreply.github.com
License: Apache Software License 2.0
Keywords: nbdev jupyter notebook python
Classifier: Development Status :: 4 - Beta
Classifier: Intended Audience :: Developers
Classifier: Natural Language :: English
Classifier: Programming Language :: Python :: 3.11
Classifier: Programming Language :: Python :: 3.12
Classifier: License :: OSI Approved :: Apache Software License
Requires-Python: >=3.11
License-File: LICENSE
Requires-Dist: cjm_error_handling
Requires-Dist: fastapi
Requires-Dist: psutil
Requires-Dist: uvicorn
Requires-Dist: httpx
Requires-Dist: typer
Requires-Dist: pyyaml
Provides-Extra: dev
Dynamic: author
Dynamic: author-email
Dynamic: classifier
Dynamic: description
Dynamic: description-content-type
Dynamic: home-page
Dynamic: keywords
Dynamic: license
Dynamic: license-file
Dynamic: provides-extra
Dynamic: requires-dist
Dynamic: requires-python
Dynamic: summary
